flowws_unit_cell/BasisSelection.py
flowws_unit_cell/CenterSpaceGroup.py
flowws_unit_cell/Projection.py
flowws_unit_cell/__init__.py
flowws_unit_cell/version.py
flowws_unit_cell-0.1.0.dist-info/LICENSE.txt
flowws_unit_cell-0.1.0.dist-info/METADATA
flowws_unit_cell-0.1.0.dist-info/WHEEL
flowws_unit_cell-0.1.0.dist-info/entry_points.txt
flowws_unit_cell-0.1.0.dist-info/top_level.txt
flowws_unit_cell-0.1.0.dist-info/RECORD
