Metadata-Version: 2.1
Name: flowws-unit-cell
Version: 0.1.0
Summary: Stage-based scientific workflows for crystal unit cell identification
Home-page: UNKNOWN
Author: Matthew Spellings
Author-email: mspells@umich.edu
License: BSD-3-Clause
Platform: UNKNOWN
Classifier: Development Status :: 3 - Alpha
Classifier: License :: OSI Approved :: BSD License
Classifier: Programming Language :: Python :: 3
Requires-Python: >=3
Requires-Dist: flowws
Requires-Dist: flowws-analysis
Requires-Dist: flowws-freud
Requires-Dist: freud-analysis
Requires-Dist: plato-draw
Requires-Dist: rowan
Requires-Dist: scikit-learn
Requires-Dist: spglib
